lyra2re2_hash.cp35-win_amd64.pyd
lyra2re3_hash.cp35-win_amd64.pyd
lyra2re_hash.cp35-win_amd64.pyd
lyra2re2_hash-1.2.1.dist-info/LICENSE
lyra2re2_hash-1.2.1.dist-info/METADATA
lyra2re2_hash-1.2.1.dist-info/WHEEL
lyra2re2_hash-1.2.1.dist-info/top_level.txt
lyra2re2_hash-1.2.1.dist-info/RECORD
