Metadata-Version: 2.1
Name: lyra2re2-hash
Version: 1.2.1
Summary: Bindings for Lyra2RE2 proof of work used by Vertcoin
Home-page: https://github.com/metalicjames/lyra2re-hash-python
Author: James Lovejoy
Author-email: jameslovejoy1@gmail.com
License: UNKNOWN
Platform: UNKNOWN
